LICENSE
README.rst
setup.py
sqlormx_generator/__init__.py
sqlormx_generator/base.py
sqlormx_generator/mysql.py
sqlormx_generator/postgresql.py
sqlormx_generator/sqlit.py
sqlormx_generator.egg-info/PKG-INFO
sqlormx_generator.egg-info/SOURCES.txt
sqlormx_generator.egg-info/dependency_links.txt
sqlormx_generator.egg-info/not-zip-safe
sqlormx_generator.egg-info/requires.txt
sqlormx_generator.egg-info/top_level.txt