Metadata-Version: 2.1
Name: sqlormx-generator
Version: 0.0.1
Summary: sqlx-orm-generator is a model code generator from tables for sqlormx_generator.
Home-page: https://gitee.com/summry/sqlx-orm-generator
Author: summry
Author-email: xiazhongbiao@126.com
License: UNKNOWN
Keywords: SQL,sqlormx,python
Platform: UNKNOWN
Requires-Python: >=3.5
License-File: LICENSE
